pyproxyroulette/__init__.py
pyproxyroulette/app.py
pyproxyroulette/core.py
pyproxyroulette/defaults.py
pyproxyroulette/exceptions.py
pyproxyroulette/pool.py
pyproxyroulette/proxy.py
pyproxyroulette-0.4.9.dist-info/LICENSE.txt
pyproxyroulette-0.4.9.dist-info/METADATA
pyproxyroulette-0.4.9.dist-info/WHEEL
pyproxyroulette-0.4.9.dist-info/top_level.txt
pyproxyroulette-0.4.9.dist-info/RECORD
