Metadata-Version: 2.1
Name: pyproxyroulette
Version: 0.4.9
Summary: A simple wrapper for Requests to randomly select proxies
Home-page: https://github.com/Tortuginator/pyproxyroulette
Author: Tortuginator
License: UNKNOWN
Project-URL: Documentation, https://github.com/Tortuginator/pyproxyroulette
Project-URL: Code, https://github.com/Tortuginator/pyproxyroulette
Project-URL: Issue tracker, https://github.com/Tortuginator/pyproxyroulette/issues
Keywords: PROXY,REQUESTS,PYPROXY,ROULETTE,CRAWLER,SCRAPER,PROXIFY
Platform: any
Classifier: Development Status :: 4 - Beta
Classifier: Intended Audience :: Developers
Classifier: Intended Audience :: Science/Research
Classifier: License :: OSI Approved :: MIT License
Classifier: Topic :: Scientific/Engineering
Classifier: Topic :: System :: Networking
Classifier: Topic :: Internet :: WWW/HTTP
Classifier: Programming Language :: Python :: 3
Classifier: Programming Language :: Python :: 3.4
Classifier: Programming Language :: Python :: 3.5
Classifier: Programming Language :: Python :: 3.6
Requires-Python: !=2.*,!=3.0.*,!=3.1.*,!=3.2.*,!=3.3.*
Requires-Dist: Requests
